pandola/__init__.py
pandola/core/DataFrame.py
pandola/core/Index.py
pandola/core/Location.py
pandola/core/Series.py
pandola/core/__init__.py
pandola/util/__init__.py
pandola/util/message.py
tests/__init__.py
tests/test.py
pandola-0.1.2.dist-info/METADATA
pandola-0.1.2.dist-info/WHEEL
pandola-0.1.2.dist-info/top_level.txt
pandola-0.1.2.dist-info/RECORD
